elementary_vectors/__init__.py
elementary_vectors/functions.py
elementary_vectors/utility.py
elementary_vectors-2.2.dist-info/licenses/LICENSE
elementary_vectors-2.2.dist-info/METADATA
elementary_vectors-2.2.dist-info/WHEEL
elementary_vectors-2.2.dist-info/top_level.txt
elementary_vectors-2.2.dist-info/RECORD
